[
  {
    "title" : "TITLE OF NOTE 1",
    "content" : "content of note 1. this is dummy content and meaningless. content of note 1. this is dummy content and meaningless"
  },
  {
    "title" : "TITLE OF NOTE 2",
    "content" : "content of note 1. this is dummy content and meaningless. content of note 1. this is dummy content and meaningless"
  },
  {
    "title" : "TITLE OF NOTE 3",
    "content" : "content of note 1. this is dummy content and meaningless. content of note 1. this is dummy content and meaningless"
  },
  {
    "title" : "TITLE OF NOTE 4",
    "content" : "content of note 1. this is dummy content and meaningless. content of note 1. this is dummy content and meaningless"
  },
  {
    "title" : "TITLE OF NOTE 5",
    "content" : "content of note 1. this is dummy content and meaningless. content of note 1. this is dummy content and meaningless"
  },
  {
    "title" : "TITLE OF NOTE 6",
    "content" : "content of note 1. this is dummy content and meaningless. content of note 1. this is dummy content and meaningless"
  }



]